{
    "book_id": "622932",
    "mid": "/m/02xq0j",
    "title": "According to Mary Magdalene",
    "author": "Marianne Fredriksson",
    "publication_date": "1997-03",
    "genres": [
        "Fiction",
        "Novel"
    ],
    "text": " The story offers a feminist perspective on the person of Christ and on the beginnings of the Christian Church. Since it presents Jesus as merely a human being and deviates from the orthodox biblical portrayal of the Son of Man, the novel was severely criticised by mainstream Christians. sv:Enligt Maria Magdalena"
}